krange/__init__.py
krange/krange.py
krange-1.1.dist-info/LICENSE
krange-1.1.dist-info/METADATA
krange-1.1.dist-info/WHEEL
krange-1.1.dist-info/top_level.txt
krange-1.1.dist-info/RECORD
