Metadata-Version: 2.1
Name: krange
Version: 1.1
Summary: A range / interval package.
Home-page: https://github.com/pamendez/Range-Kata
Author: Pedro Arturo Mendez Cruz, Jean Michael Cuadrado, Belkis Yazmin Vásquez Peña
Author-email: 1088438@est.intec.edu.do, 1076992@est.intec.edu.do, 1085273@est.intec.edu.do
License: UNKNOWN
Platform: UNKNOWN
Classifier: Programming Language :: Python :: 3
Classifier: License :: OSI Approved :: MIT License
Classifier: Operating System :: OS Independent
Requires-Python: >=3.10.1
License-File: LICENSE
